{
    "all": [
        [
            "2021-07-26T01:06:02",
            76998
        ],
        [
            "2021-07-26T20:10:04",
            77570
        ],
        [
            "2021-07-28T01:29:28",
            78337
        ],
        [
            "2021-07-29T01:25:08",
            78805
        ],
        [
            "2021-07-30T01:23:55",
            79242
        ],
        [
            "2021-07-30T02:45:47",
            79265
        ],
        [
            "2021-07-31T01:28:10",
            79751
        ]
    ],
    "ci_light": [
        [
            "2021-07-26T01:06:02",
            1849
        ],
        [
            "2021-07-26T20:10:04",
            1856
        ],
        [
            "2021-07-28T01:29:28",
            1858
        ],
        [
            "2021-07-29T01:25:08",
            1873
        ],
        [
            "2021-07-30T01:23:55",
            1877
        ],
        [
            "2021-07-30T02:45:47",
            1878
        ],
        [
            "2021-07-31T01:28:10",
            1881
        ]
    ],
    "dart": [
        [
            "2021-07-26T01:06:02",
            649
        ],
        [
            "2021-07-26T20:10:04",
            650
        ],
        [
            "2021-07-28T01:29:28",
            651
        ],
        [
            "2021-07-29T01:25:08",
            652
        ],
        [
            "2021-07-30T01:23:55",
            653
        ],
        [
            "2021-07-30T02:45:47",
            654
        ],
        [
            "2021-07-31T01:28:10",
            654
        ]
    ],
    "documentation": [
        [
            "2021-07-26T01:06:02",
            6373
        ],
        [
            "2021-07-26T20:10:04",
            6405
        ],
        [
            "2021-07-28T01:29:28",
            6502
        ],
        [
            "2021-07-29T01:25:08",
            6600
        ],
        [
            "2021-07-30T01:23:55",
            6703
        ],
        [
            "2021-07-30T02:45:47",
            6712
        ],
        [
            "2021-07-31T01:28:10",
            6801
        ]
    ],
    "dotnet": [
        [
            "2021-07-26T01:06:02",
            215501
        ],
        [
            "2021-07-26T20:10:04",
            215546
        ],
        [
            "2021-07-28T01:29:28",
            215612
        ],
        [
            "2021-07-29T01:25:08",
            215655
        ],
        [
            "2021-07-30T01:23:55",
            215692
        ],
        [
            "2021-07-30T02:45:47",
            215693
        ],
        [
            "2021-07-31T01:28:10",
            215735
        ]
    ],
    "go": [
        [
            "2021-07-26T01:06:02",
            2247
        ],
        [
            "2021-07-26T20:10:04",
            2256
        ],
        [
            "2021-07-28T01:29:28",
            2306
        ],
        [
            "2021-07-29T01:25:08",
            2326
        ],
        [
            "2021-07-30T01:23:55",
            2332
        ],
        [
            "2021-07-30T02:45:47",
            2334
        ],
        [
            "2021-07-31T01:28:10",
            2345
        ]
    ],
    "java": [
        [
            "2021-07-26T01:06:02",
            14354
        ],
        [
            "2021-07-26T20:10:04",
            14423
        ],
        [
            "2021-07-28T01:29:28",
            14674
        ],
        [
            "2021-07-29T01:25:08",
            14827
        ],
        [
            "2021-07-30T01:23:55",
            14894
        ],
        [
            "2021-07-30T02:45:47",
            14901
        ],
        [
            "2021-07-31T01:28:10",
            15011
        ]
    ],
    "javascript": [
        [
            "2021-07-26T01:06:02",
            22037
        ],
        [
            "2021-07-26T20:10:04",
            22186
        ],
        [
            "2021-07-28T01:29:28",
            22489
        ],
        [
            "2021-07-29T01:25:08",
            22726
        ],
        [
            "2021-07-30T01:23:55",
            22945
        ],
        [
            "2021-07-30T02:45:47",
            22966
        ],
        [
            "2021-07-31T01:28:10",
            23062
        ]
    ],
    "php": [
        [
            "2021-07-26T01:06:02",
            1299
        ],
        [
            "2021-07-26T20:10:04",
            1300
        ],
        [
            "2021-07-28T01:29:28",
            1301
        ],
        [
            "2021-07-29T01:25:08",
            1306
        ],
        [
            "2021-07-30T01:23:55",
            1310
        ],
        [
            "2021-07-30T02:45:47",
            1311
        ],
        [
            "2021-07-31T01:28:10",
            1311
        ]
    ],
    "python": [
        [
            "2021-07-26T01:06:02",
            11978
        ],
        [
            "2021-07-26T20:10:04",
            12114
        ],
        [
            "2021-07-28T01:29:28",
            12392
        ],
        [
            "2021-07-29T01:25:08",
            12554
        ],
        [
            "2021-07-30T01:23:55",
            12640
        ],
        [
            "2021-07-30T02:45:47",
            12647
        ],
        [
            "2021-07-31T01:28:10",
            12745
        ]
    ],
    "ruby": [
        [
            "2021-07-26T01:06:02",
            965
        ],
        [
            "2021-07-26T20:10:04",
            978
        ],
        [
            "2021-07-28T01:29:28",
            985
        ],
        [
            "2021-07-29T01:25:08",
            985
        ],
        [
            "2021-07-30T01:23:55",
            989
        ],
        [
            "2021-07-30T02:45:47",
            990
        ],
        [
            "2021-07-31T01:28:10",
            991
        ]
    ],
    "rust": [
        [
            "2021-07-26T01:06:02",
            690
        ],
        [
            "2021-07-26T20:10:04",
            691
        ],
        [
            "2021-07-28T01:29:28",
            694
        ],
        [
            "2021-07-29T01:25:08",
            696
        ],
        [
            "2021-07-30T01:23:55",
            698
        ],
        [
            "2021-07-30T02:45:47",
            699
        ],
        [
            "2021-07-31T01:28:10",
            699
        ]
    ],
    "salesforce": [
        [
            "2021-07-26T01:06:02",
            4751
        ],
        [
            "2021-07-26T20:10:04",
            4784
        ],
        [
            "2021-07-28T01:29:28",
            4851
        ],
        [
            "2021-07-29T01:25:08",
            4901
        ],
        [
            "2021-07-30T01:23:55",
            4949
        ],
        [
            "2021-07-30T02:45:47",
            4953
        ],
        [
            "2021-07-31T01:28:10",
            4986
        ]
    ],
    "scala": [
        [
            "2021-07-26T01:06:02",
            640
        ],
        [
            "2021-07-26T20:10:04",
            641
        ],
        [
            "2021-07-28T01:29:28",
            642
        ],
        [
            "2021-07-29T01:25:08",
            642
        ],
        [
            "2021-07-30T01:23:55",
            642
        ],
        [
            "2021-07-30T02:45:47",
            643
        ],
        [
            "2021-07-31T01:28:10",
            643
        ]
    ],
    "swift": [
        [
            "2021-07-26T01:06:02",
            519
        ],
        [
            "2021-07-26T20:10:04",
            520
        ],
        [
            "2021-07-28T01:29:28",
            521
        ],
        [
            "2021-07-29T01:25:08",
            521
        ],
        [
            "2021-07-30T01:23:55",
            521
        ],
        [
            "2021-07-30T02:45:47",
            522
        ],
        [
            "2021-07-31T01:28:10",
            522
        ]
    ],
    "terraform": [
        [
            "2021-07-26T01:06:02",
            2885
        ],
        [
            "2021-07-26T20:10:04",
            2905
        ],
        [
            "2021-07-28T01:29:28",
            2969
        ],
        [
            "2021-07-29T01:25:08",
            3052
        ],
        [
            "2021-07-30T01:23:55",
            3062
        ],
        [
            "2021-07-30T02:45:47",
            3063
        ],
        [
            "2021-07-31T01:28:10",
            3070
        ]
    ]
}